doohickey/__init__.py
doohickey/doohickey.py
doohickey/utils/__init__.py
doohickey/utils/exceptions.py
doohickey/utils/logger.py
doohickey/utils/version.py
doohickey-0.0.1.dist-info/LICENSE.md
doohickey-0.0.1.dist-info/METADATA
doohickey-0.0.1.dist-info/WHEEL
doohickey-0.0.1.dist-info/top_level.txt
doohickey-0.0.1.dist-info/RECORD
