Metadata-Version: 2.1
Name: doohickey
Version: 0.0.1
Summary: A Python package that creates personal tools and frameworks I commonly use
Home-page: https://github.com/MSAdministrator/doohickey
Author: MSAdministrator
Author-email: rickardja@live.com
License: MIT
Keywords: carcass
Platform: UNKNOWN
Requires-Python: >=2.6, !=3.0.*, !=3.1.*, !=3.2.*, <4
Requires-Dist: pyyaml
